gazze/__init__.py
gazze/applications.py
gazze/cli.py
gazze/concurrency.py
gazze/datastructures.py
gazze/encoders.py
gazze/exception_handlers.py
gazze/exceptions.py
gazze/middleware/asyncexitstack.py
gazze/params.py
gazze/requests.py
gazze/responses.py
gazze/routing.py
gazze/types.py
gazze/utils.py
gazze-0.1.21.dist-info/METADATA
gazze-0.1.21.dist-info/WHEEL
gazze-0.1.21.dist-info/entry_points.txt
gazze-0.1.21.dist-info/RECORD
